odoo/addons/l10n_fr_chorus_facturx/README.rst
odoo/addons/l10n_fr_chorus_facturx/__init__.py
odoo/addons/l10n_fr_chorus_facturx/__manifest__.py
odoo/addons/l10n_fr_chorus_facturx/i18n/es.po
odoo/addons/l10n_fr_chorus_facturx/i18n/fr.po
odoo/addons/l10n_fr_chorus_facturx/i18n/l10n_fr_chorus_factur-x.pot
odoo/addons/l10n_fr_chorus_facturx/i18n/l10n_fr_chorus_facturx.pot
odoo/addons/l10n_fr_chorus_facturx/i18n/nb_NO.po
odoo/addons/l10n_fr_chorus_facturx/models/__init__.py
odoo/addons/l10n_fr_chorus_facturx/models/account_move.py
odoo/addons/l10n_fr_chorus_facturx/models/chorus_flow.py
odoo/addons/l10n_fr_chorus_facturx/models/res_company.py
odoo/addons/l10n_fr_chorus_facturx/readme/CONFIGURE.md
odoo/addons/l10n_fr_chorus_facturx/readme/CONTRIBUTORS.md
odoo/addons/l10n_fr_chorus_facturx/readme/DESCRIPTION.md
odoo/addons/l10n_fr_chorus_facturx/readme/USAGE.md
odoo/addons/l10n_fr_chorus_facturx/static/description/icon.png
odoo/addons/l10n_fr_chorus_facturx/static/description/index.html
odoo_addon_l10n_fr_chorus_facturx-18.0.1.0.0.4.dist-info/METADATA
odoo_addon_l10n_fr_chorus_facturx-18.0.1.0.0.4.dist-info/WHEEL
odoo_addon_l10n_fr_chorus_facturx-18.0.1.0.0.4.dist-info/top_level.txt
odoo_addon_l10n_fr_chorus_facturx-18.0.1.0.0.4.dist-info/RECORD
